setup.cfg
setup.py
prophet_tool/__init__.py
prophet_tool/проверка_элементов.py
prophet_tool/работа_с_файлами.py
prophet_tool/терминал.py
prophet_tool.egg-info/PKG-INFO
prophet_tool.egg-info/SOURCES.txt
prophet_tool.egg-info/dependency_links.txt
prophet_tool.egg-info/not-zip-safe
prophet_tool.egg-info/top_level.txt