Metadata-Version: 2.1
Name: prophet-tool
Version: 0.4
Summary: Мои личные инструменты
Author-email: prophet.incorporated@gmail.com
